anime_api/__init__.py
anime_api/apis/__init__.py
anime_api/apis/anime_facts_rest_api/__init__.py
anime_api/apis/anime_facts_rest_api/objects.py
anime_api/apis/animechan/__init__.py
anime_api/apis/animechan/objects.py
anime_api/apis/animu/__init__.py
anime_api/apis/animu/objects.py
anime_api/apis/animu/operators.py
anime_api/apis/animu/types.py
anime_api/apis/catboys/__init__.py
anime_api/apis/catboys/objects.py
anime_api/apis/hmtai/__init__.py
anime_api/apis/hmtai/objects.py
anime_api/apis/hmtai/types.py
anime_api/apis/kyoko/__init__.py
anime_api/apis/kyoko/objects.py
anime_api/apis/neko_love/__init__.py
anime_api/apis/neko_love/obejcts.py
anime_api/apis/neko_love/types.py
anime_api/apis/nekobot/__init__.py
anime_api/apis/nekobot/objects.py
anime_api/apis/nekobot/types.py
anime_api/apis/nekos_api/__init__.py
anime_api/apis/nekos_api/objects.py
anime_api/apis/nekos_api/types.py
anime_api/apis/nekos_api/utils.py
anime_api/apis/nekos_best/__init__.py
anime_api/apis/nekos_best/objects.py
anime_api/apis/nekos_best/types.py
anime_api/apis/nekos_life/__init__.py
anime_api/apis/nekos_life/objects.py
anime_api/apis/nekos_life/types.py
anime_api/apis/nekos_moe/__init__.py
anime_api/apis/nekos_moe/objects.py
anime_api/apis/nekos_moe/types.py
anime_api/apis/studio_ghibli_api/__init__.py
anime_api/apis/studio_ghibli_api/objects.py
anime_api/apis/trace_moe/__init__.py
anime_api/apis/trace_moe/objects.py
anime_api/apis/waifu_im/__init__.py
anime_api/apis/waifu_im/objects.py
anime_api/apis/waifu_im/types.py
anime_api/apis/waifu_pics/__init__.py
anime_api/apis/waifu_pics/objects.py
anime_api/apis/waifu_pics/types.py
anime_api/exceptions.py
anime_api/utils.py
anime_api-1.0.1.dist-info/LICENSE.md
anime_api-1.0.1.dist-info/METADATA
anime_api-1.0.1.dist-info/WHEEL
anime_api-1.0.1.dist-info/RECORD
