Metadata-Version: 2.1
Name: anime-api
Version: 1.0.1
Summary: A collection of wrappers for anime-related APIs
Author: Neki
Author-email: 84998222+Nekidev@users.noreply.github.com
Requires-Python: >=3.7,<4
Classifier: Programming Language :: Python :: 3
Classifier: Programming Language :: Python :: 3.7
Classifier: Programming Language :: Python :: 3.8
Classifier: Programming Language :: Python :: 3.9
Classifier: Programming Language :: Python :: 3.10
Classifier: Programming Language :: Python :: 3.11
Requires-Dist: pykakasi (>=2.2.1,<3.0.0)
Requires-Dist: python-dateutil (>=2.8.2,<3.0.0)
Requires-Dist: requests (>=2.28.1,<3.0.0)
